LICENSE
README.md
target_bigquery/__init__.py
target_bigquery/batch_job.py
target_bigquery/constants.py
target_bigquery/core.py
target_bigquery/gcs_stage.py
target_bigquery/proto_gen.py
target_bigquery/storage_write.py
target_bigquery/streaming_insert.py
target_bigquery/target.py
z3_target_bigquery-0.7.2.dist-info/LICENSE
z3_target_bigquery-0.7.2.dist-info/METADATA
z3_target_bigquery-0.7.2.dist-info/WHEEL
z3_target_bigquery-0.7.2.dist-info/entry_points.txt
z3_target_bigquery-0.7.2.dist-info/RECORD
