Metadata-Version: 2.1
Name: z3-target-bigquery
Version: 0.7.2
Summary: z3-target-bigquery is a Singer target for BigQuery. It supports storage write, GCS, streaming, and batch load methods. Built with the Meltano SDK.
Home-page: https://github.com/z3z1ma/target-bigquery
License: MIT
Keywords: ELT,BigQuery
Author: Alex Butler
Author-email: butler.alex2010@gmail.com
Requires-Python: >=3.8,<3.12
Classifier: Development Status :: 4 - Beta
Classifier: Environment :: Console
Classifier: Intended Audience :: Developers
Classifier: License :: OSI Approved :: MIT License
Classifier: Operating System :: OS Independent
Classifier: Programming Language :: Python :: 3
Classifier: Programming Language :: Python :: 3.8
Classifier: Programming Language :: Python :: 3.9
Classifier: Programming Language :: Python :: 3.10
Classifier: Programming Language :: Python :: 3.11
Classifier: Topic :: Software Development :: Libraries :: Python Modules
Classifier: Typing :: Typed
Requires-Dist: google-cloud-bigquery[bqstorage] (>=3.4.1,<4)
Requires-Dist: google-cloud-storage (>=2.7.0,<3)
Requires-Dist: grpcio-status (>=1.51.1,<2)
Requires-Dist: grpcio-tools (>=1.51.1,<2)
Requires-Dist: orjson (>=3.7.2,<4)
Requires-Dist: requests (>=2.25.1)
Requires-Dist: singer-sdk (>=0.22.0,<0.23.0)
Requires-Dist: tenacity (>=8.0.1,<9)
Project-URL: Repository, https://github.com/z3z1ma/target-bigquery
